safronauts-0.1.2.dist-info/METADATA
safronauts-0.1.2.dist-info/WHEEL
safronauts/__init__.py
safronauts/_core.abi3.so
safronauts/_core.pyi
safronauts/differential/__init__.py
safronauts/differential/discrete.py
safronauts/py.typed
safronauts-0.1.2.dist-info/RECORD
