Metadata-Version: 2.4
Name: safronauts
Version: 0.1.2
Requires-Dist: twine>=6.1.0
Summary: Add your description here
Author-email: safronautsgh <safronauts@gmail.com>
Requires-Python: >=3.12.11
